README.txt
alterootheme.lazydays-configure.zcml
setup.cfg
setup.py
alterootheme/__init__.py
alterootheme.lazydays.egg-info/PKG-INFO
alterootheme.lazydays.egg-info/SOURCES.txt
alterootheme.lazydays.egg-info/dependency_links.txt
alterootheme.lazydays.egg-info/entry_points.txt
alterootheme.lazydays.egg-info/namespace_packages.txt
alterootheme.lazydays.egg-info/not-zip-safe
alterootheme.lazydays.egg-info/paster_plugins.txt
alterootheme.lazydays.egg-info/requires.txt
alterootheme.lazydays.egg-info/top_level.txt
alterootheme/lazydays/__init__.py
alterootheme/lazydays/configure.zcml
alterootheme/lazydays/lazydays.zip
alterootheme/lazydays/notes.txt
alterootheme/lazydays/profiles.zcml
alterootheme/lazydays/setuphandlers.py
alterootheme/lazydays/skins.zcml
alterootheme/lazydays/tests.py
alterootheme/lazydays/version.txt
alterootheme/lazydays/browser/__init__.py
alterootheme/lazydays/browser/__init__.pyo
alterootheme/lazydays/browser/configure.zcml
alterootheme/lazydays/browser/interfaces.py
alterootheme/lazydays/browser/viewlet.pt
alterootheme/lazydays/browser/viewlets.py
alterootheme/lazydays/browser/images/firefox.jpg
alterootheme/lazydays/browser/images/bg/balloons.gif
alterootheme/lazydays/browser/images/bg/bullet.gif
alterootheme/lazydays/browser/images/bg/footer.jpg
alterootheme/lazydays/browser/images/bg/gradient.jpg
alterootheme/lazydays/browser/images/bg/header.jpg
alterootheme/lazydays/browser/images/bg/header_left.jpg
alterootheme/lazydays/browser/images/bg/header_right.jpg
alterootheme/lazydays/browser/images/icons/exclamation.gif
alterootheme/lazydays/browser/images/icons/go.gif
alterootheme/lazydays/browser/images/icons/quote.gif
alterootheme/lazydays/browser/images/icons/stop.gif
alterootheme/lazydays/browser/stylesheets/html.css
alterootheme/lazydays/browser/stylesheets/layout.css
alterootheme/lazydays/browser/stylesheets/main.css
alterootheme/lazydays/browser/stylesheets/print.css
alterootheme/lazydays/browser/templates/footer.pt
alterootheme/lazydays/browser/templates/header.pt
alterootheme/lazydays/browser/templates/sections.pt
alterootheme/lazydays/lazydays/LICENSE.txt
alterootheme/lazydays/lazydays/help.html
alterootheme/lazydays/lazydays/index.html
alterootheme/lazydays/lazydays/print.html
alterootheme/lazydays/lazydays/tags.html
alterootheme/lazydays/lazydays/css/html.css
alterootheme/lazydays/lazydays/css/layout.css
alterootheme/lazydays/lazydays/css/print.css
