Metadata-Version: 1.0
Name: alterootheme.lazydays
Version: 1.0a
Summary: A Theme for Plone 3.0 based on OpenWebDesign.org Lazy Days theme
Home-page: http://themes.alteroo.com
Author: David Bain
Author-email: david.bain@alteroo.com
License: GPL
Keywords: web zope plone theme
Platform: UNKNOWN
Classifier: Framework :: Plone
Classifier: Framework :: Zope2
Classifier: Framework :: Zope3
Classifier: Programming Language :: Python
Classifier: Topic :: Software Development :: Libraries :: Python Modules
